{"question": {"@xmlns": "http://schemas.assemblee-nationale.fr/referentiel", "@xmlns:xsi": "http://www.w3.org/2001/XMLSchema-instance", "@xsi:type": "QuestionGouvernement_Type", "uid": "QANR5L15QG503", "identifiant": {"numero": "503", "regime": "5eme R\ufffdpublique", "legislature": "15"}, "type": "QG", "indexationAN": {"rubrique": "s\u00e9curit\u00e9 des biens et des personnes", "teteAnalyse": null, "ANALYSE": {"ANA": "lutte contre la radicalisation"}}, "auteur": {"identite": {"acteurRef": "PA719488", "mandatRef": "PM722676"}, "groupe": {"organeRef": "PO730970", "abrege": "MODEM", "developpe": "Mouvement D\u00e9mocrate et apparent\u00e9s"}}, "minInt": {"abrege": "Int\u00e9rieur", "developpe": "Minist\u00e8re de l\u2019int\u00e9rieur"}, "minAttribs": {"minAttrib": {"denomination": {"abrege": "Int\u00e9rieur", "developpe": "Minist\u00e8re de l\u2019int\u00e9rieur"}}}, "textesReponse": {"texteReponse": {"infoJO": {"typeJO": "JO_DEBAT", "dateJO": "25/01/2018"}, "texte": "</p><p align=\"CENTER\"> LUTTE CONTRE LA RADICALISATION <a name=PG1></a> </p><br><strong>M.\u00a0le pr\u00e9sident. </strong>La parole est \u00e0 M.\u00a0Philippe Berta, pour le groupe du Mouvement d\u00e9mocrate et apparent\u00e9s.<br><br><strong>M.\u00a0Philippe Berta. </strong>Monsieur le ministre de l'int\u00e9rieur, vendredi dernier, un homme \u00e2g\u00e9 de trente-trois ans, soup\u00e7onn\u00e9 de pr\u00e9parer un attentat et connu pour avoir pr\u00eat\u00e9 all\u00e9geance au groupe \u00c9tat islamique, a \u00e9t\u00e9 interpell\u00e9 dans le Gard. Il s'agit du premier attentat d\u00e9jou\u00e9 par la Direction g\u00e9n\u00e9rale de la s\u00e9curit\u00e9 int\u00e9rieure, la DGSI, en ce d\u00e9but d'ann\u00e9e. Je tiens \u00e0 saluer la grande qualit\u00e9 du travail de vos services qui a permis l'interpellation puis la mise en examen pour \u00ab\u00a0association de malfaiteurs terroriste criminelle\u00a0\u00bb de cet individu.<br><br>\u00c0 cette occasion, le pr\u00e9fet du Gard, Didier Lauga, a rappel\u00e9 par voie de presse des chiffres inqui\u00e9tants pour notre d\u00e9partement. Au niveau national, le Gard se situe au quatri\u00e8me rang des d\u00e9partements les plus radicalis\u00e9s et la zone de d\u00e9fense sud, qui comprend les r\u00e9gions Occitanie et Provence-Alpes-C\u00f4te d'Azur, repr\u00e9sente plus de la moiti\u00e9 des affaires terroristes.<br><br>Dans ce contexte, le nouveau plan d'action contre la radicalisation et le terrorisme est plus qu'attendu pour lutter contre le mal \u00e0 sa racine.<br><br>Un plan contre la radicalisation devrait \u00eatre pr\u00e9sent\u00e9 \u00e0 l'issue d'un comit\u00e9 interminist\u00e9riel en ce d\u00e9but d'ann\u00e9e. Nous attendons qu'il traduise l'urgente et indispensable impulsion du Gouvernement pour endiguer le ph\u00e9nom\u00e8ne de radicalisation. Il doit \u00e9galement permettre \u00e0 l'ensemble des acteurs, au niveau national mais \u00e9galement sur le terrain, de se coordonner afin d'assurer la continuit\u00e9 de cette priorit\u00e9 pour la s\u00e9curit\u00e9 nationale.<br><br>Monsieur le ministre, pouvez-vous nous confirmer l'\u00e9ch\u00e9ance de f\u00e9vrier\u00a02018 pour la pr\u00e9sentation du plan d'action contre la radicalisation\u00a0? Quelles sont vos priorit\u00e9s en vue de l'\u00e9laboration de ce plan, ainsi que le r\u00f4le que vous envisagez pour les territoires\u00a0? <i>(Applaudissements sur les bancs des groupes MODEM et REM.)</i><br><br><strong>M.\u00a0le pr\u00e9sident. </strong>La parole est \u00e0 M.\u00a0le ministre d'\u00c9tat, ministre de l'int\u00e9rieur.<br><br><strong>M.\u00a0G\u00e9rard Collomb,</strong><i> ministre d'\u00c9tat, ministre de l'int\u00e9rieur . </i>Monsieur le pr\u00e9sident, mesdames et messieurs les d\u00e9put\u00e9s, je tiens tout d'abord \u00e0 saluer l'action de nos services qui, pour la premi\u00e8re fois cette ann\u00e9e, viennent de d\u00e9jouer un attentat.<br><br>Le d\u00e9fi reste \u00e9lev\u00e9, et je confirme les chiffres que vous avez rappel\u00e9s, monsieur le d\u00e9put\u00e9 \u2013 je tiens en effet \u00e0 toujours faire preuve de la plus grande transparence sur ces sujets. Aujourd'hui, dans le d\u00e9partement du Gard, 258 personnes sont inscrites au fichier des signalements pour la pr\u00e9vention de la radicalisation \u00e0 caract\u00e8re terroriste \u2013 FSPRT. Cela donne une id\u00e9e de l'ampleur des d\u00e9fis que nous devrons relever.<br><br>Avec M. le Premier ministre, nous tiendrons un comit\u00e9 interminist\u00e9riel en f\u00e9vrier pour lutter contre la radicalisation. Nous souhaitons avancer de mani\u00e8re globale.<br><br>Ainsi, nous travaillerons avec le ministre de l'\u00e9ducation nationale, car c'est d'abord \u00e0 la base qu'il faut apprendre un certain nombre de valeurs et emp\u00eacher que les gens ne glissent sur des pentes de plus en plus mauvaises.<br><br>Nous travaillerons \u00e9galement avec Mme\u00a0la ministre des solidarit\u00e9s et de la sant\u00e9, car un certain nombre de situations trouvent leur origine dans des situations psychologiques difficiles. Nous enverrons ensemble une circulaire aux agences r\u00e9gionales de sant\u00e9 et aux pr\u00e9fets afin qu'ils puissent collaborer et \u00e9viter ainsi qu'un certain nombre de personnes ne d\u00e9rapent.<br> <p>"}}, "cloture": {"codeCloture": "REP_PUB", "libelleCloture": "R\u00e9ponse publi\u00e9e", "dateCloture": "25/01/2018", "infoJO": {"typeJO": "JO_DEBAT", "dateJO": "25/01/2018", "pageJO": "394"}}}}