{"question": {"@xmlns": "http://schemas.assemblee-nationale.fr/referentiel", "@xmlns:xsi": "http://www.w3.org/2001/XMLSchema-instance", "@xsi:type": "QuestionGouvernement_Type", "uid": "QANR5L15QG278", "identifiant": {"numero": "278", "regime": "5eme R\ufffdpublique", "legislature": "15"}, "type": "QG", "indexationAN": {"rubrique": "terrorisme", "teteAnalyse": null, "ANALYSE": {"ANA": "accompagnement des victimes du terrorisme"}}, "auteur": {"identite": {"acteurRef": "PA335054", "mandatRef": "PM723254"}, "groupe": {"organeRef": "PO730946", "abrege": "NG", "developpe": "Nouvelle Gauche"}}, "minInt": {"abrege": "Justice", "developpe": "Minist\u00e8re de la justice"}, "minAttribs": {"minAttrib": {"denomination": {"abrege": "Justice", "developpe": "Minist\u00e8re de la justice"}}}, "textesReponse": {"texteReponse": {"infoJO": {"typeJO": "JO_DEBAT", "dateJO": "15/11/2017"}, "texte": "</p><p align=\"CENTER\"> ACCOMPAGNEMENT DES VICTIMES DU TERRORISME <a name=PG5></a> </p><br><strong>M.\u00a0le pr\u00e9sident. </strong>La parole est \u00e0 Mme\u00a0Marietta Karamanli, pour le groupe Nouvelle Gauche.<br><br><strong>Mme\u00a0Marietta Karamanli. </strong>Monsieur le Premier ministre, la Nation a comm\u00e9mor\u00e9 avec \u00e9motion les attentats du 13\u00a0novembre\u00a02015. Comm\u00e9morer signifie \u00eatre en m\u00e9moire avec ceux qui ont alors \u00e9t\u00e9 victimes du terrorisme dans notre pays et ceux qui, ces derni\u00e8res ann\u00e9es, l'ont \u00e9t\u00e9 partout ailleurs o\u00f9 il a frapp\u00e9.<br><br>Notre devoir de m\u00e9moire est guid\u00e9 par le sentiment de devoir la justice aux nombreuses victimes ainsi qu'\u00e0 leurs familles. Notre victoire, ici, contre ceux qui arment, nous la devons \u00e0 notre rassemblement et \u00e0 une volont\u00e9, partag\u00e9e par l'ensemble des forces politiques et sociales, de r\u00e9parer le mal fait et de lutter contre ceux qui le font.<br><br>Nos pens\u00e9es vont tout d'abord aux victimes. Certes, il y a toujours, apr\u00e8s les \u00e9v\u00e9nements, une grande \u00e9motion ainsi qu'une forte mobilisation pour sauver et accompagner les victimes comme pour lutter, sur notre sol, contre les actes de guerre.<br><br>Nous savons aussi qu'avec le temps, l'\u00e9motion s'\u00e9mousse et les victimes deviennent peu \u00e0 peu des administr\u00e9s qui doivent se battre pour continuer \u00e0 vivre. Alors m\u00eame que l'indemnisation se fait attendre, trouver un logement ou reprendre une vie professionnelle sont autant de gageures.<br><br>Alors que, jusqu'en juin 2017, un secr\u00e9tariat d'\u00c9tat aux victimes \u00e9tait leur interlocuteur, la volont\u00e9 de suivre et de coordonner leurs justes demandes n'a plus, depuis lors, d'incarnation politique.<br><br>Parall\u00e8lement, au plan international, la lutte contre les agresseurs \u2013\u00a0les Daech et autres\u00a0\u2013 demande une coop\u00e9ration renforc\u00e9e entre les \u00c9tats europ\u00e9ens et une collaboration sans failles avec les \u00c9tats tiers, notamment du Moyen-Orient.<br><br>Ces derniers s'av\u00e8rent des partenaires engag\u00e9s mais parfois fragiles, car mus par des mouvements internes contradictoires, en raison parfois d'une insuffisance d\u00e9mocratique.<br><br>Monsieur le Premier ministre, ma demande est double. Pouvez-vous tout d'abord nous dire si vous entendez cr\u00e9er un dispositif plac\u00e9 sous votre autorit\u00e9 et disposant des moyens n\u00e9cessaires \u00e0 la coordination, \u00e0 l'accompagnement et \u00e0 la juste r\u00e9paration dus aux victimes du terrorisme\u00a0?<br><br>Pouvez-vous enfin nous indiquer quelles orientations diplomatiques fortes en mati\u00e8re de coop\u00e9ration avec les \u00c9tats eux-m\u00eames confront\u00e9s au terrorisme et devant en rendre compte \u00e0 leurs populations vous entendez promouvoir, au c\u00f4t\u00e9 du Pr\u00e9sident de la R\u00e9publique, afin d'en convaincre nos partenaires europ\u00e9ens\u00a0? <i>(Applaudissements sur les bancs des groupes NG et GDR.)</i><br><br><strong>M.\u00a0le pr\u00e9sident. </strong>La parole est \u00e0 Mme\u00a0la garde des sceaux, ministre de la justice.<br><br><strong>Mme\u00a0Nicole Belloubet,</strong><i> garde des sceaux, ministre de la justice. </i>Madame la d\u00e9put\u00e9e, par un d\u00e9cret de mai\u00a02017, le Premier ministre a confi\u00e9 au garde des Sceaux la responsabilit\u00e9 de la conduite et de la coordination de la politique d'aide aux victimes.<br><br>Une d\u00e9l\u00e9gu\u00e9e interminist\u00e9rielle \u00e0 l'aide aux victimes, Mme \u00c9lisabeth Pelsez, a, par la suite, \u00e9t\u00e9 nomm\u00e9e\u00a0: elle assure aujourd'hui pleinement, et avec beaucoup d'efficacit\u00e9, ses fonctions.<br><br>Son r\u00f4le consiste \u00e0 coordonner tout le travail accompli autour de l'aide aux victimes et \u00e0 accompagner chacune d'entre elles dans la situation dans laquelle elle se trouve. Les c\u00e9r\u00e9monies, \u00e0 la fois dignes et tr\u00e8s \u00e9mouvantes, auxquelles nous avons assist\u00e9 hier t\u00e9moignent du besoin ressenti par chacune des victimes d'\u00eatre r\u00e9ellement suivie\u00a0: c'est pr\u00e9cis\u00e9ment ce que fait Mme Pelsez.<br><br>Elle a fix\u00e9 un certain nombre de priorit\u00e9s que je vais vous d\u00e9tailler et que nous avons ent\u00e9rin\u00e9 lors d'un comit\u00e9 interminist\u00e9riel \u00e0 l'aide aux victimes qui s'est tenu le 12\u00a0novembre dernier sous la pr\u00e9sidence du Premier ministre. <br><br>Ces priorit\u00e9s sont les suivantes. <i>(Murmures sur les bancs du groupe Les R\u00e9publicains.)</i><br><br>Je vous remercie. <i>(Applaudissements sur les bancs des groupes REM et MODEM. - Protestations sur les bancs du groupe LR.)</i><br><br><strong>Un d\u00e9put\u00e9 du groupe REM .</strong> Ce sont les questions au Gouvernement\u00a0: \u00e9coutez les r\u00e9ponses\u00a0!<br><br><strong>M.\u00a0Erwan Balanant.</strong> Pour bavarder, allez \u00e0 la buvette\u00a0!<br><br><strong>M.\u00a0Fabien Di\u00a0Filippo.</strong> Madame la ministre, vous n'\u00eates pas l\u00e0 pour distribuer des bons points, mais pour r\u00e9pondre aux questions\u00a0!<br><br><strong>Mme\u00a0Nicole Belloubet,</strong><i> garde des sceaux . </i>Il s'agit d'une part de prendre en charge le suivi psychologique de chacune des victimes. Dans cette perspective, Mme Pelsez a d\u00e9cid\u00e9 de cr\u00e9er un centre de r\u00e9silience qui permettra d'accompagner, en termes de ressources et de suivi psychologique, chacune des victimes.<br><br>J'ai \u00e9galement pu me rendre compte que les victimes avaient besoin d'\u00eatre suivies en termes de retour \u00e0 l'emploi et \u00e0 la formation. Beaucoup de jeunes ayant subi des traumatismes ont, en effet, besoin d'un tel suivi.<br><br>Mme Pelsez a donc, d'autre part, pass\u00e9 des conventions avec P\u00f4le emploi et travaille avec Agn\u00e8s Buzyn comme avec Muriel P\u00e9nicaud sur ce sujet. Nous aurons, enfin, une action europ\u00e9enne tr\u00e8s puissante. <i>(Applaudissements sur les bancs des groupes REM et MODEM, ainsi que sur plusieurs bancs du groupe LC.)</i><br> <p>"}}, "cloture": {"codeCloture": "REP_PUB", "libelleCloture": "R\u00e9ponse publi\u00e9e", "dateCloture": "15/11/2017", "infoJO": {"typeJO": "JO_DEBAT", "dateJO": "15/11/2017", "pageJO": "4843"}}}}