{"question": {"@xmlns": "http://schemas.assemblee-nationale.fr/referentiel", "@xmlns:xsi": "http://www.w3.org/2001/XMLSchema-instance", "@xsi:type": "QuestionGouvernement_Type", "uid": "QANR5L15QG3302", "identifiant": {"numero": "3302", "regime": "5eme R\ufffdpublique", "legislature": "15"}, "type": "QG", "indexationAN": {"rubrique": "industrie", "teteAnalyse": null, "ANALYSE": {"ANA": "Violences \u00e0 Mayotte"}}, "auteur": {"identite": {"acteurRef": "PA724827", "mandatRef": "PM754304"}, "groupe": {"organeRef": "PO730964", "abrege": "LAREM", "developpe": "La R\u00e9publique en Marche"}}, "minInt": {"abrege": "Outre-mer", "developpe": "Minist\u00e8re des outre-mer"}, "minAttribs": {"minAttrib": {"denomination": {"abrege": "Outre-mer", "developpe": "Minist\u00e8re des outre-mer"}}}, "textesReponse": {"texteReponse": {"infoJO": {"typeJO": "JO_DEBAT", "dateJO": "16/09/2020"}, "texte": "</p><p align=\"CENTER\"> VIOLENCES \u00c0 MAYOTTE <a name=PG22></a> </p><br><strong>M.\u00a0le pr\u00e9sident. </strong>La parole est \u00e0 Mme\u00a0Ramlati Ali.<br><br><strong>Mme\u00a0Ramlati Ali. </strong>Monsieur le ministre des outre-mer, Mayotte conna\u00eet une flamb\u00e9e de violence sans pr\u00e9c\u00e9dent. En effet, depuis plus d'un mois, dans ce territoire, de tr\u00e8s vives tensions se mat\u00e9rialisent par des actes de violence physique et sociale, qui se multiplient quotidiennement, accentu\u00e9s par une grave crise socio-\u00e9conomique. <br><br>Le probl\u00e8me est s\u00e9v\u00e8re et suscite une tr\u00e8s forte inqui\u00e9tude au sein de la population. Il ne se passe pas un jour sans que l'on assiste au triste spectacle de voitures d\u00e9grad\u00e9es, br\u00fbl\u00e9es, de rackets d'automobilistes, de motards, de pillages et d'affrontements entre bandes rivales. Cette d\u00e9linquance de jeunes est de plus en plus violente. Certains sont m\u00eame arm\u00e9s de machettes et s\u00e8ment le chaos. De plus, la col\u00e8re des habitants contre les immigr\u00e9s clandestins s'exacerbe.<br><br>Mayotte se trouve donc dans une situation de pourrissement. Les habitants sont apeur\u00e9s, exasp\u00e9r\u00e9s, et d\u00e9cident de se prot\u00e9ger par eux-m\u00eames. La rentr\u00e9e scolaire est mouvement\u00e9e et l'\u00e9conomie se fragilise toujours davantage. Il ne se passe pas un jour sans que soit annonc\u00e9e une nouvelle gr\u00e8ve sociale, touchant tous les secteurs d'activit\u00e9. Je pense tout particuli\u00e8rement aux employ\u00e9s du supermarch\u00e9 Jumbo Score, dont le mouvement dure depuis plus de soixante jours. Dans deux jours, l'intersyndicale de Mayotte commencera une gr\u00e8ve d'une dur\u00e9e ind\u00e9termin\u00e9e.<br><br>Pour apaiser ces tensions, des \u00e9lus ont fait des propositions, notamment celle de recourir aux militaires et de d\u00e9ployer \u00e0 Mayotte un \u00ab\u00a0plan Harpie\u00a0\u00bb, \u00e0 l'instar de l'op\u00e9ration Harpie men\u00e9e en Guyane contre l'orpaillage clandestin. Cette possibilit\u00e9 avait d'ailleurs \u00e9t\u00e9 \u00e9voqu\u00e9e par le Pr\u00e9sident de la R\u00e9publique, Emmanuel Macron, lors de sa rencontre avec les maires d'outre-mer \u00e0 l'\u00c9lys\u00e9e, en f\u00e9vrier\u00a02019, dans le cadre du grand d\u00e9bat national.<br><br>La direction territoriale de la police nationale, nouveau service d\u00e9concentr\u00e9 de l'\u00c9tat \u00e0 Mayotte, ne demande qu'\u00e0 voir ses \u00e9quipes renforc\u00e9es. Force est de constater qu'en d\u00e9pit des efforts de l'\u00c9tat, l'arsenal disponible pour la lutte contre l'ins\u00e9curit\u00e9 dans l'\u00eele est insuffisant au regard de la situation incendiaire que conna\u00eet Mayotte. Le d\u00e9sespoir et le sentiment d'abandon sont tr\u00e8s forts au sein de la population mahoraise, exc\u00e9d\u00e9e par l'insuffisance des r\u00e9actions face \u00e0 cette violence sans fin. Les Mahorais sont des Fran\u00e7ais\u00a0; ils attendent des r\u00e9sultats concrets et des mesures ad\u00e9quates\u2026 <br><br><strong>M.\u00a0le pr\u00e9sident.</strong> Merci, madame la d\u00e9put\u00e9e.<br><br><strong>Mme\u00a0Ramlati Ali. </strong>\u2026afin de r\u00e9tablir la loi et l'ordre sur le territoire mahorais. <i>(Applaudissements sur plusieurs bancs du groupe LaREM. \u2013 M.\u00a0Philippe Naillet applaudit \u00e9galement.)</i><br><br><strong>M.\u00a0le pr\u00e9sident. </strong>La parole est \u00e0 M.\u00a0le ministre des outre-mer.<br><br><strong>M.\u00a0S\u00e9bastien Lecornu,</strong><i> ministre des outre-mer. </i>Parlons franchement\u00a0: la situation \u00e0 Mayotte est extraordinairement pr\u00e9occupante. Malheureusement, elle ne date pas d'hier. <br><br>Pour r\u00e9pondre aux d\u00e9fis qui nous attendent et \u00e9laborer des solutions, il nous faut regarder les choses en face et en parler sans tabou. <br><br>Premi\u00e8rement, nous r\u00e9pondons par une mont\u00e9e en puissance r\u00e9galienne \u2013\u00a0cette affaire est \u00e9videmment suivie par le ministre de l'int\u00e9rieur. Je rappelle que plus de 1\u00a0200\u00a0militaires de la gendarmerie et policiers nationaux sont d\u00e9sormais d\u00e9ploy\u00e9s \u00e0 Mayotte, ce qui repr\u00e9sente un effectif suppl\u00e9mentaire de pr\u00e8s de 400\u00a0agents depuis 2015. L'autorit\u00e9 judiciaire a aussi b\u00e9n\u00e9fici\u00e9 de renforts. <br><br>Le deuxi\u00e8me d\u00e9fi \u00e0 relever est celui de l'immigration \u2013\u00a0sur ce point aussi, il faut se d\u00e9barrasser des tabous. Nous savons tr\u00e8s bien que l'op\u00e9ration Shikandra, dont les r\u00e9sultats en 2019 ont \u00e9t\u00e9 tout \u00e0 fait significatifs, a malheureusement \u00e9t\u00e9 g\u00ean\u00e9e par le confinement et la crise de la covid. Pour produire ses effets, ce dispositif doit regagner en puissance, en lien avec les forces arm\u00e9es d\u00e9ploy\u00e9es dans le cadre de l'action de l'\u00c9tat en mer, notamment la marine nationale. Comme vous le savez, madame la d\u00e9put\u00e9e, il nous faut aussi parler vrai avec les Comores\u00a0: une initiative diplomatique forte a donc \u00e9t\u00e9 lanc\u00e9e afin d'obtenir des r\u00e9sultats en mati\u00e8re d'immigration. <br><br>Enfin, comme je l'ai d\u00e9j\u00e0 indiqu\u00e9 \u00e0 l'ensemble des parlementaires et \u00e9lus d\u00e9partementaux lors de la r\u00e9union tr\u00e8s r\u00e9publicaine qui s'est tenue il y a quinze jours, alors que nous approchons du dixi\u00e8me anniversaire de la d\u00e9partementalisation de Mayotte, nous devons dresser sereinement, calmement, tranquillement, un premier bilan de celle-ci, notamment concernant les comp\u00e9tences transf\u00e9r\u00e9es aux collectivit\u00e9s territoriales telles que l'aide sociale \u00e0 l'enfance ou la protection maternelle et infantile. La s\u00e9curit\u00e9, c'est aussi ces d\u00e9fis qu'il nous faut relever tous ensemble. <i>(Applaudissements sur plusieurs bancs des groupes LaREM et MODEM.)</i><br> <p>"}}, "cloture": {"codeCloture": "REP_PUB", "libelleCloture": "R\u00e9ponse publi\u00e9e", "dateCloture": "16/09/2020", "infoJO": {"typeJO": "JO_DEBAT", "dateJO": "16/09/2020", "pageJO": "6042"}}}}