{"question": {"@xmlns": "http://schemas.assemblee-nationale.fr/referentiel", "@xmlns:xsi": "http://www.w3.org/2001/XMLSchema-instance", "@xsi:type": "QuestionGouvernement_Type", "uid": "QANR5L15QG1098", "identifiant": {"numero": "1098", "regime": "5eme R\ufffdpublique", "legislature": "15"}, "type": "QG", "indexationAN": {"rubrique": "sports", "teteAnalyse": null, "ANALYSE": {"ANA": "coupe du monde et pratique sportive"}}, "auteur": {"identite": {"acteurRef": "PA720430", "mandatRef": "PM722962"}, "groupe": {"organeRef": "PO730958", "abrege": "FI", "developpe": "La France insoumise"}}, "minInt": {"abrege": "Premier ministre", "developpe": "Premier ministre"}, "minAttribs": {"minAttrib": {"denomination": {"abrege": "Premier ministre", "developpe": "Premier ministre"}}}, "textesReponse": {"texteReponse": {"infoJO": {"typeJO": "JO_DEBAT", "dateJO": "18/07/2018"}, "texte": "</p><p align=\"CENTER\"> COUPE DU MONDE ET PRATIQUE SPORTIVE <a name=PG1></a> </p><br><strong>M.\u00a0le pr\u00e9sident. </strong>La parole est \u00e0 M.\u00a0Ugo Bernalicis, pour le groupe La France insoumise.<br><br><strong>M.\u00a0Ugo Bernalicis. </strong>Quelle comp\u00e9tition de dingue\u00a0! Quelle victoire\u00a0! Bravo et merci \u00e0 cette \u00e9quipe de France de football qui a remport\u00e9 cette deuxi\u00e8me \u00e9toile\u00a0! <i>(Applaudissements sur tous les bancs.)</i><br><br>Le foot a permis de rassembler toutes les Fran\u00e7aises et tous les Fran\u00e7ais, bien au-del\u00e0 des fans. N'en d\u00e9plaise \u00e0 la \u00ab\u00a0<i>start-up nation</i>\u00a0\u00bb, ce ne sont pas des individualit\u00e9s, arch\u00e9types du mod\u00e8le du self made man, qui ont gagn\u00e9. Non, c'est la victoire d'un collectif, solidaire et fraternel, qui revendique fi\u00e8rement de proclamer \u00ab\u00a0Vive la R\u00e9publique et vive la France\u00a0!\u00a0\u00bb. (Applaudissements sur les bancs du groupe FI et sur quelques bancs des groupes LaREM et LR.)<br><br>Le mod\u00e8le du sport fran\u00e7ais a permis d'\u00eatre sur le toit du monde depuis vingt ans. Aujourd'hui, c'est le foot, mais nous n'oublions pas le handball, le triathlon mixte dimanche dernier, le rugby \u00e0 sept f\u00e9minin, ou encore le volley-ball o\u00f9, la semaine derni\u00e8re, nous sommes devenus vice-champions du monde. <i>(M\u00eames mouvements.)</i><br><br>Ce qui a fait la force de la France doit \u00eatre p\u00e9rennis\u00e9\u00a0; or le Gouvernement le fragilise. <i>(Exclamations sur les bancs des groupes LaREM et MODEM.)</i><br><br><strong>M.\u00a0Erwan Balanant.</strong> Bravo la r\u00e9cup\u00e9ration\u00a0!<br><br><strong>M.\u00a0Fran\u00e7ois Cormier-Bouligeon.</strong> Vous feriez mieux d'expliquer les propos de votre ami Maduro qui parle honteusement de la victoire de l'Afrique\u00a0!<br><br><strong>M.\u00a0Ugo Bernalicis. </strong>Pour m\u00e9moire, le foot, ce sont 2,2\u00a0millions de personnes licenci\u00e9es en France et environ 14\u00a0000\u00a0clubs amateurs. Il y a un sentiment d'urgence, car, chaque jour, deux clubs mettent la cl\u00e9 sous la porte. Si le sport amateur est devenu, depuis trop longtemps, une variable d'ajustement pour la r\u00e9duction des d\u00e9ficits, cette victoire est pourtant aussi la sienne.<br><br>Voil\u00e0 le d\u00e9fi que nous devons relever, madame la ministre des sports\u00a0: comment accueillir \u00e0 la rentr\u00e9e prochaine, dans tous les clubs, les petites Fran\u00e7aises et les petits Fran\u00e7ais qui auront envie de pratiquer le foot et tous les autres sports,\u2026<br><br><strong>M.\u00a0Pierre Cordier.</strong> C'est vrai\u00a0!<br><br><strong>M.\u00a0Ugo Bernalicis. </strong>\u2026et qui seront peut-\u00eatre les champions de demain qui nous feront r\u00eaver\u00a0? <i>(Applaudissements sur les bancs du groupe FI et sur quelques bancs des groupes LaREM et LR.)</i><br><br>Gr\u00e2ce \u00e0 cette victoire, la F\u00e9d\u00e9ration fran\u00e7aise de football empoche notamment un ch\u00e8que de 32,5\u00a0millions d'euros de la part de la FIFA. Son pr\u00e9sident a annonc\u00e9 que 30\u00a0% de cette somme seraient revers\u00e9s aux joueurs mais n'a rien dit sur l'allocation du reste de cette enveloppe.<br><br><strong>M.\u00a0Patrick Mignola.</strong> Ce n'est pas de la r\u00e9cup\u00e9ration, c'est un hold-up\u00a0!<br><br><strong>M.\u00a0Ugo Bernalicis. </strong>Il faut que cette victoire profite \u00e0 tous et qu'elle ruisselle sur le sport amateur.<br><br>D'ailleurs, s'agissant du sport en g\u00e9n\u00e9ral, nous constatons la baisse des subventions publiques ainsi que la suppression des emplois aid\u00e9s qui venaient utilement compl\u00e9ter le b\u00e9n\u00e9volat.<br><br><strong>M.\u00a0Pierre Cordier.</strong> Eh oui\u00a0!<br><br><strong>M.\u00a0Ugo Bernalicis. </strong>Cette ann\u00e9e, le budget du Centre national pour le d\u00e9veloppement du sport \u2013\u00a0CNDS\u00a0\u2013 conna\u00eet une baisse de pr\u00e8s de 27\u00a0%, laissant les collectivit\u00e9s territoriales et les associations un peu plus seules face aux d\u00e9penses n\u00e9cessaires.<br><br><strong>M.\u00a0\u00c9ric Coquerel.</strong> Eh oui\u00a0!<br><br><strong>M.\u00a0Ugo Bernalicis. </strong>Madame la ministre, le sport amateur n'a pas \u00e0 \u00eatre rentable. Il a besoin de passes d\u00e9cisives, m\u00eame si cela co\u00fbte un pognon de dingue\u00a0! <i>(Applaudissements sur les bancs des groupes FI et GDR, ainsi que sur quelques bancs des groupes LR et NG.)</i><br><br><strong>M.\u00a0le pr\u00e9sident. </strong>La parole est \u00e0 M.\u00a0le Premier ministre.<br><br><strong>M.\u00a0Edouard Philippe,</strong><i> Premier ministre. </i>Monsieur le d\u00e9put\u00e9, je me joins \u00e9videmment \u00e0 vous, ainsi qu'au pr\u00e9sident de l'Assembl\u00e9e nationale, dans le message de f\u00e9licitations et, \u00e0 bien des \u00e9gards, d'admiration que vous adressez aux joueurs de l'\u00e9quipe de France, apr\u00e8s leur magnifique victoire dans cette comp\u00e9tition.<br><br><strong>M.\u00a0Maxime Minot.</strong> Personne n'applaudit\u00a0?<br><br><strong>M.\u00a0Edouard Philippe,</strong><i> Premier ministre . </i>Vous avez cit\u00e9 de nombreuses \u00e9quipes et de nombreuses disciplines, en insistant sur les excellents r\u00e9sultats fran\u00e7ais. Vous auriez pu, monsieur le d\u00e9put\u00e9, mentionner aussi d'autres sports \u2013\u00a0je pense notamment \u00e0 la boxe, o\u00f9 nous avons obtenu d'excellents r\u00e9sultats lors des derniers Jeux olympiques. <i>(Applaudissements sur plusieurs bancs des groupes LaREM et UDI-Agir.)</i><br><br>Non sans esprit d'\u00e0-propos, vous avez essay\u00e9 de nourrir un propos de politique g\u00e9n\u00e9rale \u00e0 partir de ce succ\u00e8s. Au fond, vous nous dites que, si cette \u00e9quipe est championne du monde, en d\u00e9pit de notre politique <i>(Sourires)</i>,\u2026<br><br><strong>M.\u00a0Ugo Bernalicis.</strong> Et de la politique des gouvernements pr\u00e9c\u00e9dents\u00a0!<br><br><strong>M.\u00a0Edouard Philippe,</strong><i> Premier ministre . </i>\u2026elle devrait permettre d'illustrer vos id\u00e9es et vos propositions. <i>(Nouveaux sourires. \u2013 Exclamations sur les bancs du groupe FI.)</i><br><br><strong>M.\u00a0Sylvain Maillard.</strong> Bien r\u00e9sum\u00e9\u00a0!<br><br><strong>Mme\u00a0Dani\u00e8le Obono.</strong> Non, la question porte sur le sport amateur\u00a0!<br><br><strong>M.\u00a0Edouard Philippe,</strong><i> Premier ministre . </i>Nous devons nous r\u00e9jouir, monsieur le d\u00e9put\u00e9 \u2013\u00a0c'est, au fond, le sens de votre question\u00a0\u2013, parce que ce qui a gagn\u00e9, dimanche, \u00e0 Moscou,\u2026<br><br><strong>M.\u00a0Ugo Bernalicis.</strong> C'est le collectif\u00a0!<br><br><strong>M.\u00a0Edouard Philippe,</strong><i> Premier ministre . </i>\u2026c'est un syst\u00e8me qui fait \u00e9merger l'excellence et qui l'assume. C'est un syst\u00e8me qui est fond\u00e9 sur un travail d'\u00e9quipe et qui l'assume. C'est un syst\u00e8me qui repose sur des prises de responsabilit\u00e9, ce qui suscite d'ailleurs parfois des critiques vives formul\u00e9es \u00e0 l'encontre de ceux qui font des choix. Je salue ici le s\u00e9lectionneur Didier Deschamps. <i>(Applaudissements sur de nombreux bancs des groupes LaREM, MODEM, LR, UDI-Agir et NG.)</i><br><br>C'est un syst\u00e8me qui repose sur une passion, une passion fran\u00e7aise pour le football. Certains la partagent depuis longtemps tandis que d\u2019autres l'ont d\u00e9couverte plus r\u00e9cemment, y compris dans vos rangs, monsieur le d\u00e9put\u00e9. <i>(Applaudissements sur les bancs des groupes LaREM et MODEM. \u2013 Exclamations sur les bancs du groupe FI.)</i> Il en est en cette mati\u00e8re comme dans d'autres\u00a0: on peut toujours y venir, et c'est tr\u00e8s bien ainsi. (Nouvelles exclamations sur les bancs du groupe FI.)<br><br><strong>M.\u00a0Pierre Cordier.</strong> Vous ne vous y int\u00e9ressez que depuis les quarts de finale\u00a0!<br><br><strong>M.\u00a0Edouard Philippe,</strong><i> Premier ministre . </i>Je conclus, monsieur le d\u00e9put\u00e9. Au fond, il n'y a rien de pire\u2026<br><br><strong>M.\u00a0Ugo Bernalicis.</strong> Que la r\u00e9cup\u00e9ration\u00a0?<br><br><strong>M.\u00a0Edouard Philippe,</strong><i> Premier ministre . </i>\u2026que d'essayer d'affirmer \u2013\u00a0vous ne l'avez pas vraiment fait, vous avez tent\u00e9 de le faire\u00a0\u2013 que des sportifs ou une \u00e9quipe d\u00e9montrent vos id\u00e9es. <i>(Exclamations sur les bancs du groupe FI et sur plusieurs bancs du groupe LR.)</i><br><br><strong>M.\u00a0Aur\u00e9lien Pradi\u00e9 et M.\u00a0Charles de\u00a0la\u00a0Verpilli\u00e8re .</strong> C'est l'h\u00f4pital qui se moque de la charit\u00e9\u00a0!<br><br><strong>M.\u00a0Edouard Philippe,</strong><i> Premier ministre . </i>Il n'y a rien de pire que d'essayer de mettre dans la bouche des sportifs des paroles que l'on aimerait dire soi-m\u00eame. <i>(M\u00eames mouvements.)</i><br><br><strong>M.\u00a0Pierre Cordier.</strong> Et les contrats aid\u00e9s\u00a0? R\u00e9pondez \u00e0 la question\u00a0!<br><br><strong>M.\u00a0Edouard Philippe,</strong><i> Premier ministre . </i>C'est la raison pour laquelle je vais faire l'inverse, monsieur le d\u00e9put\u00e9\u00a0: je vais formuler ce que j'ai entendu chez ces footballeurs, qui ont fait honneur \u00e0 leur pays\u2026<br><br><strong>Mme\u00a0Dani\u00e8le Obono.</strong> Nous parlons de sport amateur\u00a0!<br><br><strong>M.\u00a0Edouard Philippe,</strong><i> Premier ministre . </i>\u2026et qui l'ont dit tr\u00e8s t\u00f4t dans la comp\u00e9tition, avec une immense fiert\u00e9\u00a0: \u00ab\u00a0Vive la R\u00e9publique\u00a0! Vive la France\u00a0!\u00a0\u00bb <i>(Applaudissements sur les bancs des groupes LaREM, MODEM et UDI-Agir.)</i><br><br><strong>M.\u00a0Fabien Di\u00a0Filippo.</strong> Et les contrats aid\u00e9s\u00a0? Et le budget du CNDS\u00a0?<br> <p>"}}, "cloture": {"codeCloture": "REP_PUB", "libelleCloture": "R\u00e9ponse publi\u00e9e", "dateCloture": "18/07/2018", "infoJO": {"typeJO": "JO_DEBAT", "dateJO": "18/07/2018", "pageJO": "7558"}}}}