{"question": {"@xmlns": "http://schemas.assemblee-nationale.fr/referentiel", "@xmlns:xsi": "http://www.w3.org/2001/XMLSchema-instance", "@xsi:type": "QuestionGouvernement_Type", "uid": "QANR5L15QG1350", "identifiant": {"numero": "1350", "regime": "5eme R\ufffdpublique", "legislature": "15"}, "type": "QG", "indexationAN": {"rubrique": "\u00e9lections et r\u00e9f\u00e9rendums", "teteAnalyse": null, "ANALYSE": {"ANA": "r\u00e9f\u00e9rendum en Nouvelle-Cal\u00e9donie"}}, "auteur": {"identite": {"acteurRef": "PA610775", "mandatRef": "PM723170"}, "groupe": {"organeRef": "PO744425", "abrege": "UDI-AGIR", "developpe": "UDI, Agir et Ind\u00e9pendants"}}, "minInt": {"abrege": "Premier ministre", "developpe": "Premier ministre"}, "minAttribs": {"minAttrib": {"denomination": {"abrege": "Premier ministre", "developpe": "Premier ministre"}}}, "textesReponse": {"texteReponse": {"infoJO": {"typeJO": "JO_DEBAT", "dateJO": "07/11/2018"}, "texte": "</p><p align=\"CENTER\"> R\u00c9F\u00c9RENDUM EN NOUVELLE-CAL\u00c9DONIE <a name=PG9></a> </p><br><strong>M.\u00a0le pr\u00e9sident. </strong>La parole est \u00e0 M.\u00a0Philippe Gom\u00e8s, pour le groupe UDI, Agir et ind\u00e9pendants.<br><br><strong>M.\u00a0Philippe Gom\u00e8s. </strong>Le 4 novembre en Nouvelle-Cal\u00e9donie \u00e9tait une journ\u00e9e particuli\u00e8re. Monsieur le Premier ministre, vous nous avez rejoints d\u00e8s le lendemain : les Cal\u00e9doniens sont tr\u00e8s reconnaissants que le Gouvernement ait marqu\u00e9 de sa pr\u00e9sence l'importance de ce moment. <i>(Applaudissements sur les bancs du groupe UDI-Agir et sur plusieurs bancs des groupes LaREM et SOC.)</i><br><br>Le 4\u00a0novembre 2018, la Nouvelle-Cal\u00e9donie a choisi souverainement son destin, et le peuple cal\u00e9donien a \u00e9t\u00e9 \u00e0 la hauteur de ce rendez-vous avec son histoire. Il a \u00e9t\u00e9 \u00e0 la hauteur lors d'une campagne digne et responsable, alors que l'enjeu \u00e9tait d'une grande gravit\u00e9. Il a \u00e9t\u00e9 \u00e0 la hauteur comme le montre une participation exceptionnelle, soit 80\u00a0% de votants, ce qui conf\u00e8re une vraie l\u00e9gitimit\u00e9 au r\u00e9sultat de la consultation. Il a \u00e9t\u00e9 \u00e0 la hauteur par la clart\u00e9 de son choix puisqu'une forte majorit\u00e9, plus de 56\u00a0% des suffrages exprim\u00e9s, a d\u00e9cid\u00e9 de continuer \u00e0 inscrire l'histoire de la Nouvelle-Cal\u00e9donie au sein de la R\u00e9publique. <i>(Applaudissements sur plusieurs bancs des groupes UDI-Agir et LT. \u2013 Mme\u00a0Laetitia Avia applaudit \u00e9galement.)</i><br><br>\u00c0 une souverainet\u00e9 impos\u00e9e, celle issue de l'acte de prise de possession du 24 septembre 1853, vient de succ\u00e9der, ce 4 novembre 2018, une souverainet\u00e9 d\u00e9mocratiquement choisie, issue des urnes. Le lien de souverainet\u00e9 qui unit nos deux pays est d\u00e9sormais refond\u00e9. Je crois que nous devons rendre hommage au pari sur l'intelligence fait par Jacques Lafleur, Jean-Marie Tjibaou et Michel Rocard, il y a maintenant trente ans. <i>(Applaudissements sur les bancs des groupes UDI-Agir, LaREM, MODEM, LT, SOC et FI. - M. Philippe Gosselin applaudit aussi.)</i><br><br>De nouvelles \u00e9tapes nous attendent\u00a0: un deuxi\u00e8me r\u00e9f\u00e9rendum est possible d\u00e8s 2020 \u2013 il est pr\u00e9vu par l'accord de Noum\u00e9a \u2013, et un troisi\u00e8me d\u00e8s 2022. Je crois que nous devons engager rapidement un dialogue avec les ind\u00e9pendantistes, de fa\u00e7on \u00e0 voir si un nouveau consensus peut se d\u00e9gager afin de revoir au moins les modalit\u00e9s d'exercice de ces r\u00e9f\u00e9rendums. Il ne s'agit pas de remettre en cause le droit \u00e0 l'autod\u00e9termination, qui est constitutionnellement garanti, mais de revoir du moins ses modalit\u00e9s en ce qui concerne les d\u00e9lais.<br><br>Monsieur le Premier ministre, dans cette perspective, envisagez-vous d'inscrire cette question \u00e0 l'ordre du jour de la prochaine r\u00e9union du Comit\u00e9 des signataires\u00a0? (Applaudissements sur les bancs du groupe UDI-Agir.)<br><br><strong>M.\u00a0le pr\u00e9sident. </strong>La parole est \u00e0 M.\u00a0le Premier ministre.<br><br><strong>M.\u00a0Edouard Philippe,</strong><i> Premier ministre. </i>Monsieur le d\u00e9put\u00e9, vous venez de le dire remarquablement, la Nouvelle-Cal\u00e9donie a vot\u00e9, elle a vot\u00e9 clairement, massivement, sereinement. Ce vote, ce superbe exercice d\u00e9mocratique, vient valider les trente ann\u00e9es de travail effectu\u00e9es par toutes les forces politiques de Nouvelle-Cal\u00e9donie et par tous les gouvernements successifs de la R\u00e9publique. Il vient valider l'engagement de femmes et d'hommes, parfois au p\u00e9ril de leur vie.<br><br>J'ai ainsi \u00e9t\u00e9 particuli\u00e8rement frapp\u00e9, \u00e0 l'occasion de mon d\u00e9placement rapide en Nouvelle-Cal\u00e9donie, par le v\u00e9ritable engagement de l'ensemble de ceux qui ont concouru \u00e0 l'organisation du scrutin et de la campagne. Je veux dire combien le travail des 250\u00a0d\u00e9l\u00e9gu\u00e9s envoy\u00e9s en Nouvelle-Cal\u00e9donie \u2013 magistrats, hauts fonctionnaires, universitaires \u2013 a \u00e9t\u00e9 important. Ils sont all\u00e9s dans chaque commune, donc dans toute la Nouvelle-Cal\u00e9donie, dans la Grande-Terre et dans les \u00eeles, veiller \u00e0 la s\u00e9r\u00e9nit\u00e9 du scrutin lors de son d\u00e9roulement.<br><br>Je veux remercier tr\u00e8s sinc\u00e8rement les membres de la commission de contr\u00f4le pr\u00e9sid\u00e9e par M.\u00a0Francis Lamy, ainsi que ceux du comit\u00e9 des sages que nous avions cr\u00e9\u00e9 pour que la campagne respecte certaines exigences propres au dialogue. Je veux ainsi saluer le r\u00f4le jou\u00e9 par le pr\u00e9sident Jean L\u00e8ques, maire honoraire de Noum\u00e9a, qui a su, au moment o\u00f9 c'\u00e9tait n\u00e9cessaire, poser des limites \u00e0 certains de ceux qui s'exprimaient dans la campagne, en les appelant \u00e0 faire preuve de respect et d'humilit\u00e9. Lui et l'ensemble des membres de la commission des sages ont jou\u00e9 un r\u00f4le particulier et utile\u00a0; je veux les saluer.<br><br>Le scrutin s'est bien pass\u00e9, et le r\u00e9sultat de cette consultation n'est contest\u00e9 par personne. Il est l\u00e0, et il exprime la volont\u00e9 des \u00e9lecteurs de Nouvelle-Cal\u00e9donie. Personne ne veut faire comme si ce vote \u00e9tait accessoire\u00a0: il est essentiel. Vous dites qu'il est une forme de \u00ab\u00a0souverainet\u00e9 d\u00e9mocratiquement choisie\u00a0\u00bb\u00a0; je me retrouve dans ces propos\u00a0: c'est un moment essentiel pour l'histoire de la Nouvelle-Cal\u00e9donie.<br><br>Les accords de Noum\u00e9a sont la base sur laquelle s'est construit pendant trente ann\u00e9es ce processus d\u00e9mocratique. Or ces accords, et la loi organique qui en est la traduction l\u00e9gislative, pr\u00e9voient en effet que, sous certaines conditions, un deuxi\u00e8me, puis un troisi\u00e8me r\u00e9f\u00e9rendum puissent \u00eatre demand\u00e9s par un tiers du Congr\u00e8s de la Nouvelle-Cal\u00e9donie.<br><br>Ces accords nous lient, et il n'y a aucune raison de nous en \u00e9carter, \u00e0 moins de constater un consensus tr\u00e8s fort de l'ensemble des forces politiques en Nouvelle-Cal\u00e9donie. C'est un tel consensus qui a \u00e9t\u00e9 pris en consid\u00e9ration, en 1998, lorsque l'accord de Matignon a \u00e9t\u00e9 modifi\u00e9 et compl\u00e9t\u00e9 par l'accord de Noum\u00e9a. Mais en l'absence de consensus tr\u00e8s fort, ces accords nous lient, car ils sont la base sur laquelle nous construisons l'avenir de la Nouvelle-Cal\u00e9donie.<br><br>Tr\u00e8s logiquement, j'ai propos\u00e9 \u00e0 l'ensemble des membres du comit\u00e9 des signataires de se r\u00e9unir \u00e0 Paris, au mois de d\u00e9cembre, pour laisser \u00e0 l'ensemble des forces politiques le temps d'analyser les r\u00e9sultats, d'en mesurer les implications et de discuter avec leur base \u00e9lectorale avant que nous puissions tirer collectivement les enseignements de ce moment d\u00e9mocratique exceptionnel. Se poseront, \u00e9videmment, des questions institutionnelles li\u00e9es \u00e0 l'organisation des r\u00e9f\u00e9rendums suivants, si la demande en est faite. Mais d'autres questions d\u00e9passent le cadre institutionnel, \u00e9conomique et social. Lors de mon d\u00e9placement en Nouvelle-Cal\u00e9donie, j'ai \u00e9t\u00e9 tr\u00e8s sensible aux remarques que m'ont faites les \u00e9tudiants de l'universit\u00e9 de Nouvelle-Cal\u00e9donie et celles que le pr\u00e9sident de la province Nord a formul\u00e9es \u00e0 l'occasion de mon d\u00e9placement \u00e0 Kon\u00e9.<br><br>Nous aurons donc \u00e0 d\u00e9battre demain, mais \u00e0 cette heure, monsieur le d\u00e9put\u00e9, je veux dire que la qualit\u00e9 de l'organisation du scrutin, l'engagement admirable des forces politiques de Nouvelle-Cal\u00e9donie, la participation exceptionnelle font que, aujourd'hui, la France doit \u00eatre incroyablement fi\u00e8re de la Nouvelle-Cal\u00e9donie. <i>(Applaudissements sur les bancs des groupes LaREM, MODEM et UDI-Agir, sur plusieurs bancs des groupes SOC et GDR ainsi que sur quelques bancs du groupe LR.)</i><br> <p>"}}, "cloture": {"codeCloture": "REP_PUB", "libelleCloture": "R\u00e9ponse publi\u00e9e", "dateCloture": "07/11/2018", "infoJO": {"typeJO": "JO_DEBAT", "dateJO": "07/11/2018", "pageJO": "11340"}}}}